Metadata-Version: 2.1
Name: npynx
Version: 1.0
Summary: web server
Home-page: https://github.com/nbdy/npynx
Author: Pascal Eberlein
Author-email: pascal@eberlein.io
License: UNKNOWN
Keywords: web server
Platform: UNKNOWN
Classifier: Development Status :: 3 - Alpha
Classifier: Intended Audience :: Developers
Classifier: Topic :: Software Development :: Build Tools
Classifier: License :: OSI Approved :: MIT License
Classifier: Programming Language :: Python :: 3
